sportsref_nfl/__init__.py
sportsref_nfl/cli.py
sportsref_nfl/core/__init__.py
sportsref_nfl/core/game.py
sportsref_nfl/core/schedule.py
sportsref_nfl/core/scraper.py
sportsref_nfl/data/__init__.py
sportsref_nfl/data/depth_charts.py
sportsref_nfl/data/draft.py
sportsref_nfl/data/qb_elos.py
sportsref_nfl/data/rosters.py
sportsref_nfl/data/stadiums.py
sportsref_nfl/data/stats.py
sportsref_nfl/utils/__init__.py
sportsref_nfl/utils/names.py
sportsref_nfl-1.0.0.dist-info/licenses/LICENSE
sportsref_nfl-1.0.0.dist-info/METADATA
sportsref_nfl-1.0.0.dist-info/WHEEL
sportsref_nfl-1.0.0.dist-info/entry_points.txt
sportsref_nfl-1.0.0.dist-info/top_level.txt
sportsref_nfl-1.0.0.dist-info/RECORD
