Metadata-Version: 2.4
Name: sportsref-nfl
Version: 1.0.0
Summary: NFL data scraping library for Pro Football Reference
Author-email: Taylor Firman <tefirman@gmail.com>
License: MIT
Project-URL: Homepage, https://github.com/tefirman/sportsref-nfl
Project-URL: Repository, https://github.com/tefirman/sportsref-nfl
Project-URL: Issues, https://github.com/tefirman/sportsref-nfl/issues
Project-URL: Documentation, https://github.com/tefirman/sportsref-nfl#readme
Classifier: Development Status :: 4 - Beta
Classifier: Intended Audience :: Developers
Classifier: Programming Language :: Python :: 3
Classifier: Programming Language :: Python :: 3.8
Classifier: Programming Language :: Python :: 3.9
Classifier: Programming Language :: Python :: 3.10
Classifier: Programming Language :: Python :: 3.11
Classifier: Topic :: Software Development :: Libraries :: Python Modules
Classifier: Topic :: Internet :: WWW/HTTP :: Dynamic Content
Requires-Python: >=3.8
License-File: LICENSE
Requires-Dist: cloudscraper>=1.2.0
Requires-Dist: requests>=2.25.0
Requires-Dist: beautifulsoup4>=4.9.0
Requires-Dist: pandas>=1.3.0
Requires-Dist: numpy>=1.20.0
Requires-Dist: geopy>=2.1.0
Requires-Dist: selenium>=4.0.0
Provides-Extra: dev
Requires-Dist: pytest>=6.0; extra == "dev"
Requires-Dist: pytest-cov>=2.10; extra == "dev"
Requires-Dist: ruff>=0.1.0; extra == "dev"
Requires-Dist: mypy>=0.812; extra == "dev"
Requires-Dist: pre-commit>=3.0.0; extra == "dev"
Requires-Dist: types-requests>=2.25.0; extra == "dev"
Requires-Dist: types-beautifulsoup4>=4.9.0; extra == "dev"
Dynamic: license-file
